jupyterlab_gpulab_theme_light/__init__.py
jupyterlab_gpulab_theme_light/_version.py
jupyterlab_gpulab_theme_light/labextension/build_log.json
jupyterlab_gpulab_theme_light/labextension/package.json
jupyterlab_gpulab_theme_light/labextension/static/549.ebe7e7f5db40f308d9d0.js
jupyterlab_gpulab_theme_light/labextension/static/568.525d7a9098b87ce4f255.js
jupyterlab_gpulab_theme_light/labextension/static/lib_index_js.d80b9a7f49e5ae97c95c.js
jupyterlab_gpulab_theme_light/labextension/static/lib_index_js.d80b9a7f49e5ae97c95c.js.map
jupyterlab_gpulab_theme_light/labextension/static/remoteEntry.747f809b399ff3c422ad.js
jupyterlab_gpulab_theme_light/labextension/static/remoteEntry.f121c741726a71d52cb9.js
jupyterlab_gpulab_theme_light/labextension/static/remoteEntry.f121c741726a71d52cb9.js.map
jupyterlab_gpulab_theme_light/labextension/static/style.js
jupyterlab_gpulab_theme_light/labextension/static/style_index_css.3d8fb207493427ffdbd7.js
jupyterlab_gpulab_theme_light/labextension/static/style_index_css.3d8fb207493427ffdbd7.js.map
jupyterlab_gpulab_theme_light/labextension/static/vendors-node_modules_css-loader_dist_runtime_api_js-node_modules_css-loader_dist_runtime_cssW-926fd9.c48bd09f6b129aa47b51.js
jupyterlab_gpulab_theme_light/labextension/static/vendors-node_modules_css-loader_dist_runtime_api_js-node_modules_css-loader_dist_runtime_cssW-926fd9.c48bd09f6b129aa47b51.js.map
jupyterlab_gpulab_theme_light/labextension/themes/jupyterlab_gpulab_theme_light/index.css
jupyterlab_gpulab_theme_light/labextension/themes/jupyterlab_gpulab_theme_light/index.js
jupyterlab_gpulab_theme_light-0.2.0.data/data/share/jupyter/labextensions/jupyterlab_gpulab_theme_light/build_log.json
jupyterlab_gpulab_theme_light-0.2.0.data/data/share/jupyter/labextensions/jupyterlab_gpulab_theme_light/install.json
jupyterlab_gpulab_theme_light-0.2.0.data/data/share/jupyter/labextensions/jupyterlab_gpulab_theme_light/package.json
jupyterlab_gpulab_theme_light-0.2.0.dist-info/LICENSE
jupyterlab_gpulab_theme_light-0.2.0.dist-info/METADATA
jupyterlab_gpulab_theme_light-0.2.0.dist-info/WHEEL
jupyterlab_gpulab_theme_light-0.2.0.dist-info/top_level.txt
jupyterlab_gpulab_theme_light-0.2.0.dist-info/RECORD
